<?xml version="1.0" encoding="utf-8" ?>
<!--Please copy this lang file into /wwwroot/lang folder-->
<languages>
  <language name="Nederlands" id="nl">
    <mollie>
      <payment>
        <settings>
          <environment>Omgevingen</environment>
          <apikey>Api Key</apikey>
          <profileid>Profiel ID</profileid>
          <redirecturl>Redirect URL</redirecturl>
          <orderexpiresindays>Order verloopt in dagen</orderexpiresindays>
          <useordersapi>Gebruik Orders API</useordersapi>
          <usecreditcardcomponents>Gebruik Creditcard Component</usecreditcardcomponents>
          <mollieinfoheader>Mollie Info</mollieinfoheader>
          <version>Versie</version>
          <linktoprofile>Link naar Mollie Profiel (t.b.v. voor API key)</linktoprofile>
          <linktosupportpage>Link naar onze support pagina voor informatie over Mollie</linktosupportpage>
          <listedonwebsiteheader>Betaal Methodes op de website</listedonwebsiteheader>
          <listedonwebsite>Wijzigingen zijn pas zichtbaar na opslaan!</listedonwebsite>
          <marketcountry>Markt - Land</marketcountry>
          <notsupported>Niet ondersteunde valuta voor betaal methode voor markt</notsupported>
          <yes>Ja</yes>
          <no>Nee</no>
          <marketheader>Markt</marketheader>
          <currencyheader>Valuta</currencyheader>
          <paymentmethodheader>Betaal methode</paymentmethodheader>
          <requiredprofileid>Profiel ID is verplicht</requiredprofileid>
          <requiredredirecturl>Redirect URL is verplicht</requiredredirecturl>
          <requiredorderexpires>Order verloopt in dagen is verplicht</requiredorderexpires>
          <rangeorderexpires>Order verloopt in dagen moet tussen 1 en 100 liggen</rangeorderexpires>
          <settingsheader>Mollie Episerver Instellingen</settingsheader>
        </settings>
      </payment>
    </mollie>
  </language>
</languages>